ics2caldav/__init__.py
ics2caldav/patches.py
ics2caldav/redmine2owncloud.py
ics2caldav-0.2.3.dist-info/DESCRIPTION.rst
ics2caldav-0.2.3.dist-info/METADATA
ics2caldav-0.2.3.dist-info/RECORD
ics2caldav-0.2.3.dist-info/WHEEL
ics2caldav-0.2.3.dist-info/metadata.json
ics2caldav-0.2.3.dist-info/top_level.txt
