Metadata-Version: 2.0
Name: ics2caldav
Version: 0.2.3
Summary: Module to help importing .ics files to CalDAV server.
Home-page: https://github.com/wtayyeb/ics2caldav/
Author: w.Tayyeb
Author-email: tayyeb@tsaze.com
License: MIT
Keywords: ics caldav dav calendar
Platform: UNKNOWN
Classifier: Development Status :: 5 - Production/Stable
Classifier: Intended Audience :: Developers
Classifier: License :: OSI Approved :: MIT License
Classifier: Operating System :: OS Independent
Classifier: Programming Language :: Python
Classifier: Programming Language :: Python :: 2.7
Classifier: Programming Language :: Python :: 3.2
Classifier: Programming Language :: Python :: 3.3
Classifier: Programming Language :: Python :: 3.4
Classifier: Programming Language :: Python :: 3.5
Classifier: Topic :: Software Development :: Libraries :: Python Modules
Requires-Dist: caldav
Requires-Dist: ics
